esppy/__init__.py
esppy/analysis/__init__.py
esppy/analysis/corelation_analysis.py
esppy/analysis/power_spectrum.py
esppy/analysis/stats_analysis.py
esppy/analysis/time_frequency.py
esppy/cognitive_analysis_module/__init__.py
esppy/cognitive_analysis_module/cognitive_comparision.py
esppy/cognitive_analysis_module/cognitive_indexes.py
esppy/comparitive_analysis/__init__.py
esppy/data/__init__.py
esppy/data/csv.py
esppy/data/mff.py
esppy/data/task2.py
esppy/data/xlsx.py
esppy/preprocessing/__init__.py
esppy/preprocessing/epoching.py
esppy/preprocessing/filtering.py
esppy/utils/__init__.py
esppy/utils/data.py
esppy/utils/performance_eval.py
esppy/visualization/__init__.py
esppy/visualization/plot_cluster.py
esppy/visualization/plot_coherence.py
esppy/visualization/plot_cross-correlation.py
esppy/visualization/plot_eeg_signal.py
esppy/visualization/plot_heatmap.py
esppy/visualization/plot_power_spectrum.py
esppy/visualization/plot_spectogram.py
esppy/visualization/plot_time_series.py
esppy/visualization/plot_topomap.py
esppy-0.2.dist-info/LICENSE
esppy-0.2.dist-info/METADATA
esppy-0.2.dist-info/WHEEL
esppy-0.2.dist-info/top_level.txt
esppy-0.2.dist-info/RECORD
